requests_ntlm3/__init__.py
requests_ntlm3/adapters.py
requests_ntlm3/connection.py
requests_ntlm3/core.py
requests_ntlm3/dance.py
requests_ntlm3/requests_ntlm3.py
requests_ntlm3-6.1.3b1.dist-info/LICENSE
requests_ntlm3-6.1.3b1.dist-info/METADATA
requests_ntlm3-6.1.3b1.dist-info/WHEEL
requests_ntlm3-6.1.3b1.dist-info/top_level.txt
requests_ntlm3-6.1.3b1.dist-info/RECORD
