Metadata-Version: 2.1
Name: requests-ntlm3
Version: 6.1.3b1
Summary: The HTTP NTLM proxy and/or server authentication library.
Home-page: https://github.com/mchampanis/requests-ntlm3
Author: Michael Champanis
Author-email: michael.champanis@gmail.com
License: ISC
Download-URL: https://github.com/mchampanis/requests-ntlm3/archive/6.1.3b1.tar.gz
Keywords: NTLM,requests,proxy,authorization,NTLM dance
Platform: UNKNOWN
Classifier: Development Status :: 4 - Beta
Classifier: Intended Audience :: Developers
Classifier: Natural Language :: English
Classifier: Programming Language :: Python
Classifier: Programming Language :: Python :: 2.7
Classifier: Programming Language :: Python :: 3.5
Classifier: Programming Language :: Python :: 3.6
Classifier: Programming Language :: Python :: 3.7
Classifier: Programming Language :: Python :: 3.8
Classifier: License :: OSI Approved :: ISC License (ISCL)
Classifier: Operating System :: MacOS
Classifier: Operating System :: POSIX :: Linux
Classifier: Operating System :: Microsoft :: Windows
Classifier: Topic :: Software Development :: Version Control :: Git
Classifier: Programming Language :: Python :: Implementation :: CPython
Requires-Dist: requests (>=2.0.0)
Requires-Dist: ntlm-auth (>=1.0.2)
Requires-Dist: cryptography (>=1.3)
Provides-Extra: linting
Requires-Dist: flake8 ; extra == 'linting'
Requires-Dist: bandit ; extra == 'linting'
Requires-Dist: flake8-isort ; extra == 'linting'
Requires-Dist: flake8-quotes ; extra == 'linting'
Provides-Extra: testing
Requires-Dist: flask ; extra == 'testing'
Requires-Dist: pytest ; extra == 'testing'
Requires-Dist: pytest-cov ; extra == 'testing'
Requires-Dist: wheel ; extra == 'testing'
Requires-Dist: codecov ; extra == 'testing'
Requires-Dist: coverage ; extra == 'testing'
Requires-Dist: mock ; extra == 'testing'
Requires-Dist: faker ; extra == 'testing'
